README.rst
setup.py
Skeiron.egg-info/PKG-INFO
Skeiron.egg-info/SOURCES.txt
Skeiron.egg-info/dependency_links.txt
Skeiron.egg-info/entry_points.txt
Skeiron.egg-info/requires.txt
Skeiron.egg-info/top_level.txt
skeiron/__init__.py
skeiron/arelay.py
skeiron/collect.py
skeiron/distribute.py
skeiron/echo.py
skeiron/forward.py
skeiron/multiply.py
skeiron/relayfactory.py
skeiron/relayservice.py
skeiron/schema/__init__.py
skeiron/schema/collect.py
skeiron/schema/distribute.py
skeiron/schema/echo.py
skeiron/schema/forward.py
skeiron/schema/multiply.py
skeiron/schema/schema.py
tests_manual/__init__.py
tests_unit/__init__.py
tests_unit/test_collect.py
tests_unit/test_distribute.py
tests_unit/test_echo.py
tests_unit/test_forward.py
tests_unit/test_multiply.py
tests_unit/test_relayfactory.py
tests_unit/test_relayservice.py
tests_unit/test_validateconfig.py