Metadata-Version: 1.2
Name: Skeiron
Version: 0.1.3
Summary: Skeiron provides a Forwarding/Echo/Collect/Distribute service.
Home-page: https://gitlab.com/pelops/skeiron/
Author: Tobias Gawron-Deutsch
Author-email: tobias@strix.at
License: MIT license
Keywords: mqtt forward echo relay service
Platform: UNKNOWN
Classifier: Development Status :: 4 - Beta
Classifier: Environment :: Console
Classifier: Environment :: No Input/Output (Daemon)
Classifier: Intended Audience :: Developers
Classifier: Programming Language :: Python :: 3
Classifier: Topic :: Utilities
Classifier: Topic :: Home Automation
Classifier: License :: OSI Approved :: MIT License
Requires-Python: >=3.5
